[
  {
    "maintainer_name": "Sipun Ku Mahanta",
    "devices_mantaining": ["Xiaomi Redmi Note 5 Pro"],
    "country_flag": "https://emojipedia-us.s3.dualstack.us-west-1.amazonaws.com/thumbs/120/twitter/281/flag-india_1f1ee-1f1f3.png",
    "telegram_link": "https://t.me/Darkstar085",
    "github_link": "https://github.com/Sweeto143",
    "maintainer_photo": "https://avatars.githubusercontent.com/u/29405483?v=4"
  },
  {
    "maintainer_name": "Haridhayal",
    "devices_mantaining": ["Samsung Galaxy S8, S8 PLUS, Note 8 and M20"],
    "country_flag": "https://emojipedia-us.s3.dualstack.us-west-1.amazonaws.com/thumbs/120/twitter/281/flag-sri-lanka_1f1f1-1f1f0.png",
    "telegram_link": "https://t.me/Haridhayal",
    "github_link": "https://github.com/haridhayal11",
    "maintainer_photo": "https://avatars.githubusercontent.com/u/54825124?v=4"
  },
  {
    "maintainer_name": "Prajwal",
    "devices_mantaining": [
      "Xiaomi Mi 10i 5G and Former Redmi Note 7 Pro Maintainer"
    ],
    "country_flag": "https://emojipedia-us.s3.dualstack.us-west-1.amazonaws.com/thumbs/120/twitter/281/flag-india_1f1ee-1f1f3.png",
    "telegram_link": "https://t.me/Wally_West_The_Flash",
    "github_link": "https://github.com/prajwal-walia",
    "maintainer_photo": "https://avatars.githubusercontent.com/u/25847184?v=4"
  },
  {
    "maintainer_name": "Nitish",
    "devices_mantaining": [
      "Xiaomi Mi 10i 5G and Former Redmi Note 7 Pro Maintainer"
    ],
    "country_flag": "https://emojipedia-us.s3.dualstack.us-west-1.amazonaws.com/thumbs/120/twitter/281/flag-india_1f1ee-1f1f3.png",
    "telegram_link": "https://t.me/nerdfail",
    "github_link": "https://github.com/funeralfrog",
    "maintainer_photo": "https://avatars.githubusercontent.com/u/65288620?v=4"
  },
  {
    "maintainer_name": "ArmSM",
    "devices_mantaining": ["Former Moto G5S+ and Poco X3 Co-Maintainer"],
    "country_flag": "https://emojipedia-us.s3.dualstack.us-west-1.amazonaws.com/thumbs/120/twitter/281/flag-albania_1f1e6-1f1f1.png",
    "telegram_link": "https://t.me/ArmSM",
    "github_link": "https://github.com/ArmSM",
    "maintainer_photo": "https://avatars.githubusercontent.com/u/60157798?v=4"
  },
  {
    "maintainer_name": "Agus",
    "devices_mantaining": ["Poco X3 Co-Maintainer"],
    "country_flag": "https://emojipedia-us.s3.dualstack.us-west-1.amazonaws.com/thumbs/120/twitter/281/flag-indonesia_1f1ee-1f1e9.png",
    "telegram_link": "https://t.me/agustkid",
    "github_link": "https://github.com/agustkid",
    "maintainer_photo": "https://avatars.githubusercontent.com/u/58284246?v=4"
  },
  {
    "maintainer_name": "Aanya",
    "devices_mantaining": ["Xiaomi Redmi Note 7 Pro Maintainer"],
    "country_flag": "https://emojipedia-us.s3.dualstack.us-west-1.amazonaws.com/thumbs/120/twitter/281/flag-india_1f1ee-1f1f3.png",
    "telegram_link": "https://t.me/spicydoughnut",
    "github_link": "https://github.com/spicydoughnut",
    "maintainer_photo": "https://avatars.githubusercontent.com/u/72279093?v=4"
  },
  {
    "maintainer_name": "Sanya Pilot",
    "devices_mantaining": ["Xiaomi Mi Note 10"],
    "country_flag": "https://emojipedia-us.s3.dualstack.us-west-1.amazonaws.com/thumbs/120/twitter/281/flag-russia_1f1f7-1f1fa.png",
    "telegram_link": "https://t.me/alexander_baransky496",
    "github_link": "https://github.com/AlexanderBaransky",
    "maintainer_photo": "https://avatars.githubusercontent.com/u/29630471?v=4"
  },
  {
    "maintainer_name": "CakesTwix",
    "devices_mantaining": ["LeEco Le 2 and Lenovo Z5S Maintainer"],
    "country_flag": "https://emojipedia-us.s3.dualstack.us-west-1.amazonaws.com/thumbs/120/twitter/281/flag-ukraine_1f1fa-1f1e6.png",
    "telegram_link": "https://t.me/CakesTwix",
    "github_link": "https://github.com/CakesTwix",
    "maintainer_photo": "https://avatars.githubusercontent.com/u/57946485?v=4"
  },
  {
    "maintainer_name": "Deepak Jr",
    "devices_mantaining": ["OnePlus 3 and 3T Maintainer"],
    "country_flag": "https://emojipedia-us.s3.dualstack.us-west-1.amazonaws.com/thumbs/120/twitter/281/flag-india_1f1ee-1f1f3.png",
    "telegram_link": "https://t.me/Deepakjr_11",
    "github_link": "https://github.com/orgs/Sakura-Devices/people/aquariusjr10",
    "maintainer_photo": "https://avatars.githubusercontent.com/u/46277303?s=96&v=4"
  },
  {
    "maintainer_name": "Eduardo H",
    "devices_mantaining": ["OnePlus 6 and 9 Pro Maintainer"],
    "country_flag": "https://emojipedia-us.s3.dualstack.us-west-1.amazonaws.com/thumbs/120/twitter/281/flag-united-states_1f1fa-1f1f8.png",
    "telegram_link": "https://t.me/NeoTheSavage",
    "github_link": "https://github.com/THERAD1",
    "maintainer_photo": "https://avatars.githubusercontent.com/u/3580681?s=120&v=4"
  },
  {
    "maintainer_name": "Jaishnav",
    "devices_mantaining": ["Former Realme 1 Maintainer"],
    "country_flag": "https://emojipedia-us.s3.dualstack.us-west-1.amazonaws.com/thumbs/120/twitter/281/flag-india_1f1ee-1f1f3.png",
    "telegram_link": "https://t.me/CyberJalagam",
    "github_link": "https://github.com/CyberJalagam",
    "maintainer_photo": "https://avatars.githubusercontent.com/u/62203009?s=120&v=4"
  },
  {
    "maintainer_name": "Ebin",
    "devices_mantaining": [" Xiaomi Redmi 5 Maintainer"],
    "country_flag": "https://emojipedia-us.s3.dualstack.us-west-1.amazonaws.com/thumbs/120/twitter/281/flag-india_1f1ee-1f1f3.png",
    "telegram_link": "https://t.me/Ebin_A",
    "github_link": "https://github.com/arulebin/",
    "maintainer_photo": "https://avatars.githubusercontent.com/u/68118222?v=4"
  },
  {
    "maintainer_name": "Chatur",
    "devices_mantaining": ["Former Samsung Galaxy A10 and A20 Maintainer"],
    "country_flag": "https://emojipedia-us.s3.dualstack.us-west-1.amazonaws.com/thumbs/120/twitter/281/flag-mauritius_1f1f2-1f1fa.png",
    "telegram_link": "https://t.me/chatur2709",
    "github_link": "https://github.com/Chatur27",
    "maintainer_photo": "https://avatars.githubusercontent.com/u/69016406?s=96&v=4"
  },
  {
    "maintainer_name": "Henrique",
    "devices_mantaining": ["Former ASUS ZenFone 5 Maintainer"],
    "country_flag": "https://emojipedia-us.s3.dualstack.us-west-1.amazonaws.com/thumbs/120/twitter/281/flag-brazil_1f1e7-1f1f7.png",
    "telegram_link": "https://t.me/henricaodopao",
    "github_link": "https://github.com/henricaodopao",
    "maintainer_photo": "https://avatars.githubusercontent.com/u/77358650?v=4"
  },
  {
    "maintainer_name": "Abhishek",
    "devices_mantaining": ["Xiaomi Redmi Note 8 Pro Maintainer"],
    "country_flag": "https://emojipedia-us.s3.dualstack.us-west-1.amazonaws.com/thumbs/120/twitter/281/flag-india_1f1ee-1f1f3.png",
    "telegram_link": "https://t.me/abhixv",
    "github_link": "https://github.com/abhixv",
    "maintainer_photo": "https://avatars.githubusercontent.com/u/66074182?s=120&v=4"
  },
  {
    "maintainer_name": "Tanmay",
    "devices_mantaining": ["Former Realme 6 Maintainer"],
    "country_flag": "https://emojipedia-us.s3.dualstack.us-west-1.amazonaws.com/thumbs/120/twitter/281/flag-india_1f1ee-1f1f3.png",
    "telegram_link": "https://t.me/tlas01",
    "github_link": "https://github.com/Atlas78",
    "maintainer_photo": "https://avatars.githubusercontent.com/u/76161855?s=120&v=4"
  },
  { 
    "maintainer_name": "Sharan",
    "devices_mantaining": ["Realme 6 Maintainer"],
    "country_flag": "https://emojipedia-us.s3.dualstack.us-west-1.amazonaws.com/thumbs/120/twitter/281/flag-india_1f1ee-1f1f3.png",
    "telegram_link": "https://t.me/sharanpai",
    "github_link": "https://github.com/sharanpai3",
    "maintainer_photo": "https://avatars.githubusercontent.com/u/80072598?s=60&v=4"
  },
  {
    "maintainer_name": "TheDauke",
    "devices_mantaining": ["Meizu 16th and 16t Maintainer"],
    "country_flag": "https://emojipedia-us.s3.dualstack.us-west-1.amazonaws.com/thumbs/120/twitter/281/flag-kazakhstan_1f1f0-1f1ff.png",
    "telegram_link": "https://t.me/THDAS",
    "github_link": "https://github.com/thedauke",
    "maintainer_photo": "https://avatars.githubusercontent.com/u/47630438?s=120&v=4"
  },
  {
    "maintainer_name": "Alex",
    "devices_mantaining": ["Meizu 16X Maintainer"],
    "country_flag": "https://emojipedia-us.s3.dualstack.us-west-1.amazonaws.com/thumbs/120/twitter/281/flag-russia_1f1f7-1f1fa.png",
    "telegram_link": "https://t.me/c0nfid",
    "github_link": "https://github.com/c0nfid",
    "maintainer_photo": "https://avatars.githubusercontent.com/u/63528549?s=120&v=4"
  },
  {
    "maintainer_name": "hisoka_simp",
    "devices_mantaining": ["moto g(7) power Maintainer"],
    "country_flag": "https://emojipedia-us.s3.dualstack.us-west-1.amazonaws.com/thumbs/120/twitter/281/flag-germany_1f1e9-1f1ea.png",
    "telegram_link": "https://t.me/the_only_one_bruno",
    "github_link": "https://github.com/DeinMathelehrer",
    "maintainer_photo": "https://avatars.githubusercontent.com/u/58335765?v=4"
  },
  {
    "maintainer_name": "Amy",
    "devices_mantaining": ["Former moto g(7) play Maintainer"],
    "country_flag": "https://emojipedia-us.s3.dualstack.us-west-1.amazonaws.com/thumbs/120/twitter/281/flag-united-kingdom_1f1ec-1f1e7.png",
    "telegram_link": "https://t.me/amyosx",
    "github_link": "https://github.com/00p513-dev",
    "maintainer_photo": "https://avatars.githubusercontent.com/u/54113654?v=4"
  },
  {
    "maintainer_name": "Kunal",
    "devices_mantaining": ["Former Poco X2 Maintainer"],
    "country_flag": "https://emojipedia-us.s3.dualstack.us-west-1.amazonaws.com/thumbs/120/twitter/281/flag-india_1f1ee-1f1f3.png",
    "telegram_link": "https://t.me/facebook6ix9ine",
    "github_link": "https://github.com/facebook6ix9ine",
    "maintainer_photo": "https://avatars.githubusercontent.com/u/83390919?v=4"
  },
  {
    "maintainer_name": "Alisson Grizotti",
    "devices_mantaining": ["Redmi Note 7 Maintainer"],
    "country_flag": "https://emojipedia-us.s3.dualstack.us-west-1.amazonaws.com/thumbs/320/twitter/53/flag-for-brazil_1f1e7-1f1f7.png",
    "telegram_link": "https://t.me/Bagualisson",
    "github_link": "https://github.com/AlissonGrizotti",
    "maintainer_photo": "https://avatars.githubusercontent.com/u/16360520?v=4"
  },
  {
    "maintainer_name": "kiam001",
    "devices_mantaining": ["Poco X3 Pro Maintainer"],
    "country_flag": "https://emojipedia-us.s3.dualstack.us-west-1.amazonaws.com/thumbs/120/twitter/281/flag-germany_1f1e9-1f1ea.png",
    "telegram_link": "https://t.me/kiam001",
    "github_link": "https://github.com/kiam001",
    "maintainer_photo": "https://avatars.githubusercontent.com/u/10757700?v=4"
  },
  {
    "maintainer_name": "nift4",
    "devices_mantaining": ["Former Moto G5 Maintainer"],
    "country_flag": "https://emojipedia-us.s3.dualstack.us-west-1.amazonaws.com/thumbs/120/twitter/281/flag-germany_1f1e9-1f1ea.png",
    "telegram_link": "https://t.me/nift4",
    "github_link": "https://github.com/nift4",
    "maintainer_photo": "https://avatars.githubusercontent.com/u/36458596?v=4"
  },
  {
    "maintainer_name": "Ashwin DS",
    "devices_mantaining": ["Xiaomi Redmi Note 8/8T and Redmi Note 10 Maintainer"],
    "country_flag": "https://emojipedia-us.s3.dualstack.us-west-1.amazonaws.com/thumbs/120/twitter/282/flag-oman_1f1f4-1f1f2.png",
    "telegram_link": "https://t.me/dsashwin",
    "github_link": "https://github.com/geek0609",
    "maintainer_photo": "https://avatars.githubusercontent.com/u/66074607?v=4"
  },
  {
    "maintainer_name": "Karan Parashar",
    "devices_mantaining": ["Former Xiaomi Redmi Note 8/8T Co-Maintainer"],
    "country_flag": "https://emojipedia-us.s3.dualstack.us-west-1.amazonaws.com/thumbs/120/twitter/281/flag-india_1f1ee-1f1f3.png",
    "telegram_link": "https://t.me/whyredFire",
    "github_link": "https://github.com/whyredFire",
    "maintainer_photo": "https://avatars.githubusercontent.com/u/72072109?v=4"
  },
  {
    "maintainer_name": "IAmDeadlylxrd",
    "devices_mantaining": ["Redmi 8 Series"],
    "country_flag": "https://emojipedia-us.s3.dualstack.us-west-1.amazonaws.com/thumbs/120/twitter/281/flag-russia_1f1f7-1f1fa.png",
    "telegram_link": "https://t.me/deadlylxrd",
    "github_link": "https://github.com/IAmDeadlylxrd",
    "maintainer_photo": "https://avatars.githubusercontent.com/u/84336055?v=4"
  },
  {
    "maintainer_name": "mithuprince",
    "devices_mantaining": ["Xiaomi Redmi 6 Pro Maintainer"],
    "country_flag": "https://emojipedia-us.s3.dualstack.us-west-1.amazonaws.com/thumbs/120/twitter/281/flag-india_1f1ee-1f1f3.png",
    "telegram_link": "https://t.me/Pr1nc_3",
    "github_link": "https://github.com/mithuprince",
    "maintainer_photo": "https://avatars.githubusercontent.com/u/71539684?v=4"
  },
  {
    "maintainer_name": "Anoos Ragh",
    "devices_mantaining": ["Realme C2 Maintainer"],
    "country_flag": "https://emojipedia-us.s3.dualstack.us-west-1.amazonaws.com/thumbs/120/twitter/281/flag-india_1f1ee-1f1f3.png",
    "telegram_link": "https://t.me/cArN4gE_is_DeD",
    "github_link": "https://github.com/cArN4gEisDeD",
    "maintainer_photo": "https://avatars.githubusercontent.com/u/83896147?v=4" 
  },
  {
    "maintainer_name": "HMTheBoy154",
    "devices_mantaining": ["Oneplus Nord 5G and x86_64 PCs Maintainer"],
    "country_flag": "https://emojipedia-us.s3.dualstack.us-west-1.amazonaws.com/thumbs/120/twitter/282/flag-vietnam_1f1fb-1f1f3.png",
    "telegram_link": "https://t.me/hmtheboy154",
    "github_link": "https://github.com/hmtheboy154/",
    "maintainer_photo": "https://avatars.githubusercontent.com/u/39849246?v=4"
  },
  {
    "maintainer_name": "azoller1",
    "devices_mantaining": ["OnePlus 8T Maintainer"],
    "country_flag": "https://emojipedia-us.s3.dualstack.us-west-1.amazonaws.com/thumbs/120/twitter/281/flag-united-states_1f1fa-1f1f8.png",
    "telegram_link": "https://t.me/Azollr",
    "github_link": "https://github.com/azoller1/",
    "maintainer_photo": "https://avatars.githubusercontent.com/u/2552829?v=4"
  },
  {
   "maintainer_name": "Paras Dhiman",
    "devices_mantaining": ["Red Note 10 Pro Maintainer"],
    "country_flag": "https://emojipedia-us.s3.dualstack.us-west-1.amazonaws.com/thumbs/120/twitter/281/flag-india_1f1ee-1f1f3.png",
    "telegram_link": "https://t.me/Ken_kaneki_69",
    "github_link": "https://github.com/dhimanparas20/",
    "maintainer_photo": "https://avatars.githubusercontent.com/u/55368020?v=4"
  }
]
